{ "RunType": "HTTP", "Labels": "fortio-server-service:8080/ , fortio-client-deployment-6bb485cbc9-jnmb7", "StartTime": "2022-07-09T08:36:46.389837629Z", "RequestedQPS": "max", "RequestedDuration": "30s", "ActualQPS": 5010.121344947011, "ActualDuration": 30005660472, "NumThreads": 32, "Version": "1.34.1", "DurationHistogram": { "Count": 150332, "Min": 0.000951467, "Max": 0.148970901, "Sum": 960.0262359130003, "Avg": 0.006386040469846741, "StdDev": 0.0068063527143621735, "Data": [ { "Start": 0.000951467, "End": 0.001, "Percent": 0.0053215549583588324, "Count": 8 }, { "Start": 0.001, "End": 0.002, "Percent": 12.172391772876034, "Count": 18291 }, { "Start": 0.002, "End": 0.003, "Percent": 32.321794428331955, "Count": 30291 }, { "Start": 0.003, "End": 0.004, "Percent": 48.280472554080305, "Count": 23991 }, { "Start": 0.004, "End": 0.005, "Percent": 59.45573796663385, "Count": 16800 }, { "Start": 0.005, "End": 0.006, "Percent": 67.2065827634835, "Count": 11652 }, { "Start": 0.006, "End": 0.007, "Percent": 73.06295399515739, "Count": 8804 }, { "Start": 0.007, "End": 0.008, "Percent": 77.50445680227763, "Count": 6677 }, { "Start": 0.008, "End": 0.009000000000000001, "Percent": 81.17965569539419, "Count": 5525 }, { "Start": 0.009000000000000001, "End": 0.01, "Percent": 84.0226964318974, "Count": 4274 }, { "Start": 0.01, "End": 0.011, "Percent": 86.39078838836708, "Count": 3560 }, { "Start": 0.011, "End": 0.012, "Percent": 88.25200223505308, "Count": 2798 }, { "Start": 0.012, "End": 0.014, "Percent": 91.14293696618152, "Count": 4346 }, { "Start": 0.014, "End": 0.016, "Percent": 93.12854216001915, "Count": 2985 }, { "Start": 0.016, "End": 0.018000000000000002, "Percent": 94.55139291701035, "Count": 2139 }, { "Start": 0.018000000000000002, "End": 0.02, "Percent": 95.63765532288535, "Count": 1633 }, { "Start": 0.02, "End": 0.025, "Percent": 97.41971103956575, "Count": 2679 }, { "Start": 0.025, "End": 0.03, "Percent": 98.38623845887768, "Count": 1453 }, { "Start": 0.03, "End": 0.035, "Percent": 98.98956975228161, "Count": 907 }, { "Start": 0.035, "End": 0.04, "Percent": 99.34744432323124, "Count": 538 }, { "Start": 0.04, "End": 0.045, "Percent": 99.57560599207088, "Count": 343 }, { "Start": 0.045, "End": 0.05, "Percent": 99.70531889418088, "Count": 195 }, { "Start": 0.05, "End": 0.06, "Percent": 99.87494345847857, "Count": 255 }, { "Start": 0.06, "End": 0.07, "Percent": 99.93680653486949, "Count": 93 }, { "Start": 0.07, "End": 0.08, "Percent": 99.96540989277067, "Count": 43 }, { "Start": 0.08, "End": 0.09, "Percent": 99.98470052949472, "Count": 29 }, { "Start": 0.09, "End": 0.1, "Percent": 99.99334805630205, "Count": 13 }, { "Start": 0.1, "End": 0.12, "Percent": 99.99866961126041, "Count": 8 }, { "Start": 0.12, "End": 0.14, "Percent": 99.9993348056302, "Count": 1 }, { "Start": 0.14, "End": 0.148970901, "Percent": 100, "Count": 1 } ], "Percentiles": [ { "Percentile": 50, "Value": 0.004153869047619048 }, { "Percentile": 75, "Value": 0.007436124007787928 }, { "Percentile": 90, "Value": 0.013209295904279796 }, { "Percentile": 99, "Value": 0.03514572490706328 }, { "Percentile": 99.9, "Value": 0.06405032258064587 } ] }, "ErrorsDurationHistogram": { "Count": 0, "Min": 0, "Max": 0, "Sum": 0, "Avg": 0, "StdDev": 0, "Data": null, "Percentiles": null }, "Exactly": 0, "Jitter": false, "Uniform": false, "NoCatchUp": false, "RunID": 0, "AccessLoggerInfo": "", "RetCodes": { "200": 150332 }, "IPCountMap": { "10.28.8.163:8080": 32 }, "Insecure": false, "CACert": "", "Cert": "", "Key": "", "UnixDomainSocket": "", "URL": "http://fortio-server-service:8080/", "NumConnections": 1, "Compression": false, "DisableFastClient": false, "HTTP10": false, "DisableKeepAlive": false, "AllowHalfClose": false, "FollowRedirects": false, "Resolve": "", "HTTPReqTimeOut": 3000000000, "UserCredentials": "", "ContentType": "application/json", "Payload": "", "LogErrors": true, "ID": 0, "SequentialWarmup": false, "ConnReuseRange": [ 0, 0 ], "Sizes": { "Count": 150332, "Min": 156, "Max": 158, "Sum": 23473091, "Avg": 156.1416797488226, "StdDev": 0.34889301022461566, "Data": [ { "Start": 156, "End": 158, "Percent": 100, "Count": 150332 } ], "Percentiles": null }, "HeaderSizes": { "Count": 150332, "Min": 156, "Max": 158, "Sum": 23473091, "Avg": 156.1416797488226, "StdDev": 0.34889301022461566, "Data": [ { "Start": 156, "End": 158, "Percent": 100, "Count": 150332 } ], "Percentiles": null }, "SocketCount": 32, "AbortOn": 0 }
