{ "RunType": "HTTP", "Labels": "fortio-server-service:8080/ , fortio-client-deployment-6bb485cbc9-hntpv", "StartTime": "2022-07-08T16:58:10.370429515Z", "RequestedQPS": "max", "RequestedDuration": "30s", "ActualQPS": 68078.43740507321, "ActualDuration": 30000409496, "NumThreads": 32, "Version": "1.34.1", "DurationHistogram": { "Count": 2042381, "Min": 0.000082342, "Max": 0.022804522, "Sum": 959.4107326910004, "Avg": 0.00046975110554348104, "StdDev": 0.0004016242813526934, "Data": [ { "Start": 0.000082342, "End": 0.001, "Percent": 94.40026126369175, "Count": 1928013 }, { "Start": 0.001, "End": 0.002, "Percent": 99.24504781429125, "Count": 98949 }, { "Start": 0.002, "End": 0.003, "Percent": 99.75846818003106, "Count": 10486 }, { "Start": 0.003, "End": 0.004, "Percent": 99.86936815412992, "Count": 2265 }, { "Start": 0.004, "End": 0.005, "Percent": 99.91661692896673, "Count": 965 }, { "Start": 0.005, "End": 0.006, "Percent": 99.94589648062727, "Count": 598 }, { "Start": 0.006, "End": 0.007, "Percent": 99.96636278931307, "Count": 418 }, { "Start": 0.007, "End": 0.008, "Percent": 99.97772208025829, "Count": 232 }, { "Start": 0.008, "End": 0.009000000000000001, "Percent": 99.98491956202099, "Count": 147 }, { "Start": 0.009000000000000001, "End": 0.01, "Percent": 99.99045232011069, "Count": 113 }, { "Start": 0.01, "End": 0.011, "Percent": 99.99422242960544, "Count": 77 }, { "Start": 0.011, "End": 0.012, "Percent": 99.99583819081748, "Count": 33 }, { "Start": 0.012, "End": 0.014, "Percent": 99.99867801355379, "Count": 58 }, { "Start": 0.014, "End": 0.016, "Percent": 99.99921660062446, "Count": 11 }, { "Start": 0.016, "End": 0.018000000000000002, "Percent": 99.99990207507805, "Count": 14 }, { "Start": 0.02, "End": 0.022804522, "Percent": 100, "Count": 2 } ], "Percentiles": [ { "Percentile": 50, "Value": 0.0005683881004345409 }, { "Percentile": 75, "Value": 0.0008114113886321765 }, { "Percentile": 90, "Value": 0.000957225361550758 }, { "Percentile": 99, "Value": 0.0019494203074311022 }, { "Percentile": 99.9, "Value": 0.00464830984455964 } ] }, "ErrorsDurationHistogram": { "Count": 0, "Min": 0, "Max": 0, "Sum": 0, "Avg": 0, "StdDev": 0, "Data": null, "Percentiles": null }, "Exactly": 0, "Jitter": false, "Uniform": false, "NoCatchUp": false, "RunID": 0, "AccessLoggerInfo": "", "RetCodes": { "200": 2042381 }, "IPCountMap": { "10.28.0.165:8080": 32 }, "Insecure": false, "CACert": "", "Cert": "", "Key": "", "UnixDomainSocket": "", "URL": "http://fortio-server-service:8080/", "NumConnections": 1, "Compression": false, "DisableFastClient": false, "HTTP10": false, "DisableKeepAlive": false, "AllowHalfClose": false, "FollowRedirects": false, "Resolve": "", "HTTPReqTimeOut": 3000000000, "UserCredentials": "", "ContentType": "application/json", "Payload": "", "LogErrors": true, "ID": 0, "SequentialWarmup": false, "ConnReuseRange": [ 0, 0 ], "Sizes": { "Count": 2042381, "Min": 107, "Max": 107, "Sum": 218534767, "Avg": 107, "StdDev": 0, "Data": [ { "Start": 107, "End": 107, "Percent": 100, "Count": 2042381 } ], "Percentiles": null }, "HeaderSizes": { "Count": 2042381, "Min": 107, "Max": 107, "Sum": 218534767, "Avg": 107, "StdDev": 0, "Data": [ { "Start": 107, "End": 107, "Percent": 100, "Count": 2042381 } ], "Percentiles": null }, "SocketCount": 32, "AbortOn": 0 }
